nonebot_plugin_nya_cook_menu/__init__.py
nonebot_plugin_nya_cook_menu/config.py
nonebot_plugin_nya_cook_menu/data_handle.py
nonebot_plugin_nya_cook_menu/font/HYWenHei-85W.ttf
nonebot_plugin_nya_cook_menu-0.1.8.dist-info/METADATA
nonebot_plugin_nya_cook_menu-0.1.8.dist-info/WHEEL
nonebot_plugin_nya_cook_menu-0.1.8.dist-info/RECORD
