Metadata-Version: 2.1
Name: nonebot_plugin_nya_cook_menu
Version: 0.1.8
Summary: Nonebot2 喵喵自记菜谱，记录生活中的小菜谱
Home-page: https://github.com/nikissXI/nonebot_plugins/tree/main/nonebot_plugin_nya_cook_menu
License: MIT
Author: nikissXI
Author-email: 1299577815@qq.com
Requires-Python: >=3.8
Classifier: License :: OSI Approved :: MIT License
Classifier: Programming Language :: Python :: 3
Classifier: Programming Language :: Python :: 3.8
Classifier: Programming Language :: Python :: 3.9
Classifier: Programming Language :: Python :: 3.10
Classifier: Programming Language :: Python :: 3.11
Classifier: Programming Language :: Python :: 3.12
Requires-Dist: Pillow (>=9.0.0)
Requires-Dist: nonebot-adapter-onebot (>=2.0.0)
Requires-Dist: nonebot2 (>=2.0.0rc1)
Project-URL: Documentation, https://github.com/nikissXI/nonebot_plugins/tree/main/nonebot_plugin_nya_cook_menu#README.md
Project-URL: Repository, https://github.com/nikissXI/nonebot_plugins/tree/main/nonebot_plugin_nya_cook_menu
